svgsprite/__init__.py
svgsprite/svgsprite.py
svgsprite-0.1.1.dist-info/LICENSE
svgsprite-0.1.1.dist-info/METADATA
svgsprite-0.1.1.dist-info/WHEEL
svgsprite-0.1.1.dist-info/entry_points.txt
svgsprite-0.1.1.dist-info/top_level.txt
svgsprite-0.1.1.dist-info/RECORD
