Metadata-Version: 2.1
Name: svgsprite
Version: 0.1.1
Summary: Regroup your SVG files in a single sprite
Home-page: https://github.com/sephii/svgsprite
Author: Sylvain Fankhauser
Author-email: sephi@fhtagn.top
License: UNKNOWN
Platform: UNKNOWN
Classifier: Programming Language :: Python :: 3
Classifier: License :: OSI Approved :: MIT License
Classifier: Operating System :: OS Independent
Requires-Python: >=3.7
License-File: LICENSE
